tdm_loader/__init__.py
tdm_loader/tdm_loader.py
tdm_loader/tests/__init__.py
tdm_loader/tests/test_non_zip_tdm.py
tdm_loader/tests/test_time_channel.py
tdm_loader/tests/test_zip_tdm.py
tdm_loader-1.2.7.dist-info/LICENSE.txt
tdm_loader-1.2.7.dist-info/METADATA
tdm_loader-1.2.7.dist-info/WHEEL
tdm_loader-1.2.7.dist-info/top_level.txt
tdm_loader-1.2.7.dist-info/RECORD
