Metadata-Version: 2.1
Name: tdm_loader
Version: 1.2.7
Summary: Open National Instruments TDM/TDX files as NumPy structured arrays.
Home-page: https://github.com/domna/tdm_loader
Author: Florian Dobener
Author-email: florian.dobener@schroedingerscat.org
Maintainer: Florian Dobener
Maintainer-email: florian.dobener@schroedingerscat.org
License: MIT
Project-URL: Source, https://github.com/domna/tdm_loader
Project-URL: Download, https://github.com/domna/tdm_loader/releases
Project-URL: Documentation, https://tdm-loader.readthedocs.io/en/latest/
Project-URL: Changelog, https://github.com/domna/tdm_loader/blob/master/CHANGELOG.md
Project-URL: Tracker, https://github.com/domna/tdm_loader/issues
Platform: any
Classifier: Development Status :: 5 - Production/Stable
Classifier: Programming Language :: Python :: 3
Classifier: License :: OSI Approved :: MIT License
Classifier: Operating System :: OS Independent
Classifier: Intended Audience :: Science/Research
License-File: LICENSE.txt
Requires-Dist: numpy >=1.14
